Workbook
Name Aporte: Controle_de_Investimentos!$D$13
Name Patrimonio_Acumulado: Controle_de_Investimentos!$D$16
Name Qtd_Anos: Controle_de_Investimentos!$D$14
Name Rendimento_Carteira: Controle_de_Investimentos!$D$9
Name Salario: Controle_de_Investimentos!$D$8
Name Sejestao_Investimento: Controle_de_Investimentos!$D$10
Name Taxa_Mensal: Controle_de_Investimentos!$D$15

Sheet Controle_de_Investimentos
B1: Investimentos
B7: Configurações
B8: Salário: | D8: 3500
B9: Rendimento Carteira: | D9: 0.006
B10: Sujestão de Investimento (30%) | D10: =$D$8*30% -> 1050
B12: INVESTIMENTO MENSAL
B13: Quanto investir por mês? | D13: =Sejestao_Investimento -> 1050
B14: Por quantos anos? | D14: 5 | K14: =kk -> #NAME?
B15: Qual a taxa de rendimento mensal? | D15: 0.01079
B16: Quanto de patrimônio vai acumular? | D16: =FV(Taxa_Mensal,Qtd_Anos*12,Aporte*-1) -> 87965.76
B17: Quanto vai receber de dividendos por mês? | D17: =Patrimonio_Acumulado*Taxa_Mensal -> 949.15055
B19: Cenários | D19: Dividendos
B20: Quanto em 2 anos? | C20: =FV($D$15,$A26*12,$D$13*-1) -> 28589.009 | D20: =C20*Rendimento_Carteira -> 171.53405
B21: Quanto em 5 anos? | C21: =FV($D$15,$A27*12,$D$13*-1) -> 87965.76 | D21: =C21*Rendimento_Carteira -> 527.79456
B22: Quanto em 10 anos? | C22: =FV($D$15,$A28*12,$D$13*-1) -> 255448.42 | D22: =C22*Rendimento_Carteira -> 1532.6905
B23: Quanto em 20 anos? | C23: =FV($D$15,$A29*12,$D$13*-1) -> 1181458.3 | D23: =C23*Rendimento_Carteira -> 7088.7499
B24: Quanto em 30 anos? | C24: =FV($D$15,$A30*12,$D$13*-1) -> 4538278.1 | D24: =C24*Rendimento_Carteira -> 27229.669
A26: 2
A27: 5
A28: 10
A29: 20 | B29: PERFIL | C29: MODERADO
A30: 30 | B30: VALOR A SER INVESTIDO POR MÊS | C30: =Aporte -> 1050
B32: Tipo de FII | C32: Percentual Sujerido | D32: Valores
B33: PAPEL | C33: =VLOOKUP($C$29&"-"&B33,Planilha2!$A$1:$D$19,4,FALSE) -> 0.32 | D33: =Planilha2!D2*$C$30 -> 315
B34: TIJOLO | C34: =VLOOKUP($C$29&"-"&B34,Planilha2!$A$1:$D$19,4,FALSE) -> 0.4 | D34: =Planilha2!D3*$C$30 -> 525
B35: HIBRIDOS | C35: =VLOOKUP($C$29&"-"&B35,Planilha2!$A$1:$D$19,4,FALSE) -> 0.08 | D35: =Planilha2!D4*$C$30 -> 105
B36: FOFs | C36: =VLOOKUP($C$29&"-"&B36,Planilha2!$A$1:$D$19,4,FALSE) -> 0.1 | D36: =Planilha2!D5*$C$30 -> 105
B37: DESENVOLVIMENTO | C37: =VLOOKUP($C$29&"-"&B37,Planilha2!$A$1:$D$19,4,FALSE) -> 0 | D37: =Planilha2!D6*$C$30 -> 0
B38: HOTELARIAS | C38: =VLOOKUP($C$29&"-"&B38,Planilha2!$A$1:$D$19,4,FALSE) -> 0.1 | D38: =Planilha2!D7*$C$30 -> 0
D39: =SUBTOTAL(9,D33:D38) -> 1050

Sheet Planilha2
A1: CHAVE | B1: Perfil | C1: Tipo de FII | D1: %
A2: =B2&"-"&C2 -> CONSERVADOR-PAPEL | B2: CONSERVADOR | C2: PAPEL | D2: 0.3
A3: =B3&"-"&C3 -> CONSERVADOR-TIJOLO | B3: CONSERVADOR | C3: TIJOLO | D3: 0.5 | I3: %
A4: =B4&"-"&C4 -> CONSERVADOR-HIBRIDOS | B4: CONSERVADOR | C4: HIBRIDOS | D4: 0.1 | H4: MODERADO-TIJOLO | I4: =VLOOKUP(A9,$A:$D,4,FALSE) -> 0.4
A5: =B5&"-"&C5 -> CONSERVADOR-FOFs | B5: CONSERVADOR | C5: FOFs | D5: 0.1
A6: =B6&"-"&C6 -> CONSERVADOR-DESENVOLVIMENTO | B6: CONSERVADOR | C6: DESENVOLVIMENTO | D6: 0
A7: =B7&"-"&C7 -> CONSERVADOR-HOTELARIAS | B7: CONSERVADOR | C7: HOTELARIAS | D7: 0
A8: =B8&"-"&C8 -> MODERADO-PAPEL | B8: MODERADO | C8: PAPEL | D8: 0.32
A9: =B9&"-"&C9 -> MODERADO-TIJOLO | B9: MODERADO | C9: TIJOLO | D9: 0.4
A10: =B10&"-"&C10 -> MODERADO-HIBRIDOS | B10: MODERADO | C10: HIBRIDOS | D10: 0.08
A11: =B11&"-"&C11 -> MODERADO-FOFs | B11: MODERADO | C11: FOFs | D11: 0.1
A12: =B12&"-"&C12 -> MODERADO-DESENVOLVIMENTO | B12: MODERADO | C12: DESENVOLVIMENTO | D12: 0
A13: =B13&"-"&C13 -> MODERADO-HOTELARIAS | B13: MODERADO | C13: HOTELARIAS | D13: 0.1
A14: =B14&"-"&C14 -> AGRESSIVO-PAPEL | B14: AGRESSIVO | C14: PAPEL | D14: 0.5
A15: =B15&"-"&C15 -> AGRESSIVO-TIJOLO | B15: AGRESSIVO | C15: TIJOLO | D15: 0.1
A16: =B16&"-"&C16 -> AGRESSIVO-HIBRIDOS | B16: AGRESSIVO | C16: HIBRIDOS | D16: 0.05
... A19: =B19&"-"&C19 -> AGRESSIVO-HOTELARIAS | B19: AGRESSIVO | C19: HOTELARIAS | D19: 0.1
